construct/__init__.py
construct/core.py
construct/debug.py
construct/expr.py
construct/version.py
construct/lib/__init__.py
construct/lib/binary.py
construct/lib/bitstream.py
construct/lib/containers.py
construct/lib/hex.py
construct/lib/py3compat.py
construct-2.10.69.dist-info/LICENSE
construct-2.10.69.dist-info/METADATA
construct-2.10.69.dist-info/WHEEL
construct-2.10.69.dist-info/top_level.txt
construct-2.10.69.dist-info/RECORD
