Metadata-Version: 2.1
Name: construct
Version: 2.10.69
Summary: A powerful declarative symmetric parser/builder for binary data
Home-page: http://construct.readthedocs.org
Author: Arkadiusz Bulski, Tomer Filiba, Corbin Simpson
Author-email: arek.bulski@gmail.com, tomerfiliba@gmail.com, MostAwesomeDude@gmail.com
License: MIT
Project-URL: Source, https://github.com/construct/construct
Project-URL: Documentation, https://construct.readthedocs.io/en/latest/
Project-URL: Issues, https://github.com/construct/construct/issues
Keywords: construct,kaitai,declarative,data structure,struct,binary,symmetric,parser,builder,parsing,building,pack,unpack,packer,unpacker
Platform: POSIX
Platform: Windows
Classifier: Development Status :: 5 - Production/Stable
Classifier: License :: OSI Approved :: MIT License
Classifier: Intended Audience :: Developers
Classifier: Topic :: Software Development :: Libraries :: Python Modules
Classifier: Topic :: Software Development :: Build Tools
Classifier: Topic :: Software Development :: Code Generators
Classifier: Programming Language :: Python :: 3
Classifier: Programming Language :: Python :: 3.6
Classifier: Programming Language :: Python :: 3.7
Classifier: Programming Language :: Python :: 3.8
Classifier: Programming Language :: Python :: 3.9
Classifier: Programming Language :: Python :: 3.10
Classifier: Programming Language :: Python :: Implementation :: CPython
Classifier: Programming Language :: Python :: Implementation :: PyPy
Requires-Python: >=3.6
License-File: LICENSE
Provides-Extra: extras
Requires-Dist: arrow ; extra == 'extras'
Requires-Dist: cloudpickle ; extra == 'extras'
Requires-Dist: cryptography ; extra == 'extras'
Requires-Dist: enum34 ; extra == 'extras'
Requires-Dist: lz4 ; extra == 'extras'
Requires-Dist: numpy ; extra == 'extras'
Requires-Dist: ruamel.yaml ; extra == 'extras'
